ldctbench/__init__.py
ldctbench/data/LDCTMayo.py
ldctbench/data/__init__.py
ldctbench/data/info.yml
ldctbench/data/prepare_dataset.py
ldctbench/evaluate/__init__.py
ldctbench/evaluate/ldct_iqa.py
ldctbench/evaluate/utils.py
ldctbench/hub/__init__.py
ldctbench/hub/checkpoints.json
ldctbench/hub/load_model.py
ldctbench/hub/methods.py
ldctbench/hub/utils.py
ldctbench/methods/__init__.py
ldctbench/methods/base.py
ldctbench/methods/bilateral/Trainer.py
ldctbench/methods/bilateral/__init__.py
ldctbench/methods/bilateral/argparser.py
ldctbench/methods/bilateral/network.py
ldctbench/methods/cnn10/Trainer.py
ldctbench/methods/cnn10/__init__.py
ldctbench/methods/cnn10/argparser.py
ldctbench/methods/cnn10/network.py
ldctbench/methods/dugan/Trainer.py
ldctbench/methods/dugan/__init__.py
ldctbench/methods/dugan/argparser.py
ldctbench/methods/dugan/network.py
ldctbench/methods/dugan/utils.py
ldctbench/methods/qae/Trainer.py
ldctbench/methods/qae/__init__.py
ldctbench/methods/qae/argparser.py
ldctbench/methods/qae/network.py
ldctbench/methods/redcnn/Trainer.py
ldctbench/methods/redcnn/__init__.py
ldctbench/methods/redcnn/argparser.py
ldctbench/methods/redcnn/network.py
ldctbench/methods/resnet/Trainer.py
ldctbench/methods/resnet/__init__.py
ldctbench/methods/resnet/argparser.py
ldctbench/methods/resnet/network.py
ldctbench/methods/transct/Trainer.py
ldctbench/methods/transct/__init__.py
ldctbench/methods/transct/argparser.py
ldctbench/methods/transct/network.py
ldctbench/methods/wganvgg/Trainer.py
ldctbench/methods/wganvgg/__init__.py
ldctbench/methods/wganvgg/argparser.py
ldctbench/methods/wganvgg/network.py
ldctbench/scripts/__init__.py
ldctbench/scripts/download_data.py
ldctbench/scripts/hpopt.py
ldctbench/scripts/test.py
ldctbench/scripts/train.py
ldctbench/utils/__init__.py
ldctbench/utils/argparser.py
ldctbench/utils/auxiliaries.py
ldctbench/utils/metrics.py
ldctbench/utils/training_utils.py
ldct_benchmark-0.0.15.dist-info/LICENSE
ldct_benchmark-0.0.15.dist-info/METADATA
ldct_benchmark-0.0.15.dist-info/WHEEL
ldct_benchmark-0.0.15.dist-info/entry_points.txt
ldct_benchmark-0.0.15.dist-info/top_level.txt
ldct_benchmark-0.0.15.dist-info/RECORD
