Metadata-Version: 2.2
Name: ldct-benchmark
Version: 0.0.15
Summary: A benchmark for deep learning-based low dose CT image denoising
Author-email: Elias Eulig <elias.eulig@dkfz.de>
Project-URL: GitHub, https://github.com/eeulig/ldct-benchmark
Project-URL: Documentation, https://eeulig.github.io/ldct-benchmark/
Requires-Python: >=3.10
License-File: LICENSE
Requires-Dist: PyYAML
Requires-Dist: wandb
Requires-Dist: matplotlib
Requires-Dist: tqdm>4.66
Requires-Dist: scikit-image
Requires-Dist: pydicom==3.0.1
Requires-Dist: platformdirs
Requires-Dist: torchmetrics
Requires-Dist: pandas
Requires-Dist: tabulate
Requires-Dist: torch
Requires-Dist: torchvision
Provides-Extra: dev
Requires-Dist: black; extra == "dev"
Requires-Dist: isort; extra == "dev"
Requires-Dist: pytest; extra == "dev"
Requires-Dist: poethepoet; extra == "dev"
Requires-Dist: flake8; extra == "dev"
Requires-Dist: s5cmd; extra == "dev"
Provides-Extra: docs
Requires-Dist: mkdocs; extra == "docs"
Requires-Dist: mkdocs-material; extra == "docs"
Requires-Dist: mkdocstrings-python; extra == "docs"
Requires-Dist: mkdocs-gen-files; extra == "docs"
Requires-Dist: mike; extra == "docs"
